{
	"_aAlternateFileSources": null,
	"_aFiles": [
		{
			"_aMetadata": {
				"_aArchiveFileTree": [
					"de_cpl_mill.bsp",
					"de_cpl_mill.nav"
				]
			},
			"_bContainsExe": false,
			"_idRow": 351391,
			"_nDownloadCount": 6818,
			"_nFilesize": 3597382,
			"_sAnalysisResult": "File passed analysis",
			"_sAnalysisState": "done",
			"_sDescription": "",
			"_sDownloadUrl": "https://gamebanana.com/dl/351391",
			"_sFile": "de_cpl_mill_3.zip",
			"_sMd5Checksum": "",
			"_tsDateAdded": 1179961438
		}
	],
	"_aLatestUpdates": [],
	"_idRow": 101646,
	"_sName": "de_cpl_mill_noexploit",
	"_sText": "Fed up of people coming along and triggering the de_cpl_mill exploit on your server?\r\nYou NEED this version! ;)\r\n\r\nThe bsp is still named de_cpl_mill and can replace the default version on your server.\r\nThis will REMOVE the stupid low-grav exploit.\r\nClients DO NOT need to download the new version.\r\n\r\nFULL CREDIT goes to original author [DNV]Cross\r\nI just performed a simple hack using entspy"
}