{
	"_aAlternateFileSources": null,
	"_aFiles": [
		{
			"_aMetadata": {
				"_aArchiveFileTree": [
					"de_syksy.bsp",
					"de_syksy.nav"
				]
			},
			"_bContainsExe": false,
			"_idRow": 312128,
			"_nDownloadCount": 3881,
			"_nFilesize": 3622419,
			"_sAnalysisResult": "File passed analysis",
			"_sAnalysisState": "done",
			"_sDescription": "",
			"_sDownloadUrl": "https://gamebanana.com/dl/312128",
			"_sFile": "_5592-.rar",
			"_sMd5Checksum": "",
			"_tsDateAdded": 1306677994
		}
	],
	"_aLatestUpdates": [],
	"_idRow": 104222,
	"_sName": "de_syksy",
	"_sText": "Created by ICS on May 29th 2011\r\nhttp://www.ics-base.net/css_maps"
}