{
	"_aAlternateFileSources": null,
	"_aFiles": [
		{
			"_aMetadata": {
				"_aArchiveFileTree": [
					"ea_cbble_christmas.bsp"
				]
			},
			"_bContainsExe": false,
			"_idRow": 326678,
			"_nDownloadCount": 3607,
			"_nFilesize": 6847430,
			"_sAnalysisResult": "File passed analysis",
			"_sAnalysisState": "done",
			"_sDescription": "",
			"_sDownloadUrl": "https://gamebanana.com/dl/326678",
			"_sFile": "ea_cbble_christmas.rar",
			"_sMd5Checksum": "",
			"_tsDateAdded": 1260402826
		}
	],
	"_aLatestUpdates": [],
	"_idRow": 104791,
	"_sName": "ea_cbble_christmas",
	"_sText": "ENG: Put the Map in your counter strike source map folder.\r\nGER: Steck die Map in deim counter strike source Map Ordner rein.\r\n\r\nFacebook Jack: http://www.facebook.com/davidxwalter"
}