{
	"_aAlternateFileSources": null,
	"_aFiles": [
		{
			"_aMetadata": {
				"_aArchiveFileTree": [
					"aim_JJDomineYaVoy.bsp",
					"aim_jjdomineyavoy.nav"
				],
				"_sMimeType": "application/x-rar"
			},
			"_bContainsExe": false,
			"_idRow": 335079,
			"_nDownloadCount": 1175,
			"_nFilesize": 522291,
			"_sAnalysisResult": "File passed analysis",
			"_sAnalysisState": "done",
			"_sDescription": "",
			"_sDownloadUrl": "https://gamebanana.com/dl/335079",
			"_sFile": "map_31.rar",
			"_sMd5Checksum": "",
			"_tsDateAdded": 1232417400
		}
	],
	"_aLatestUpdates": [],
	"_idRow": 107715,
	"_sName": "aim_jjdomineyavoy",
	"_sText": "Simple map but good sniper fights, i try to make one beter map next time from the same zone , from my city home,this city is valencia (spain) and the map is from 50 meters from valencia street circuit F1."
}