{
	"_aAlternateFileSources": null,
	"_aFiles": [
		{
			"_aMetadata": {
				"_aArchiveFileTree": [
					"aim_uspcer.bsp",
					"aim_uspcer.cache",
					"aim_uspcer.nav"
				],
				"_sMimeType": "application/zip"
			},
			"_bContainsExe": false,
			"_idRow": 325467,
			"_nDownloadCount": 1532,
			"_nFilesize": 1538947,
			"_sAnalysisResult": "File passed analysis",
			"_sAnalysisState": "done",
			"_sDescription": "",
			"_sDownloadUrl": "https://gamebanana.com/dl/325467",
			"_sFile": "aim_uspcer.zip",
			"_sMd5Checksum": "",
			"_tsDateAdded": 1264191726
		}
	],
	"_aLatestUpdates": [],
	"_idRow": 109249,
	"_sName": "aim_uspcer",
	"_sText": "Hey,I`am create this mao for trening usp pistol...\r\nBefore to play a card include in options of a video card colour correction. A map plain, but cheerful :) I hope it to you it will be pleasant..."
}