{
	"_aAlternateFileSources": null,
	"_aFiles": [
		{
			"_aMetadata": {
				"_aArchiveFileTree": [
					"aim_uspdust.bsp"
				],
				"_sMimeType": "application/zip"
			},
			"_bContainsExe": false,
			"_idRow": 350874,
			"_nDownloadCount": 1328,
			"_nFilesize": 412939,
			"_sAnalysisResult": "File passed analysis",
			"_sAnalysisState": "done",
			"_sDescription": "",
			"_sDownloadUrl": "https://gamebanana.com/dl/350874",
			"_sFile": "aim_uspdust.zip",
			"_sMd5Checksum": "",
			"_tsDateAdded": 1181988008
		}
	],
	"_aLatestUpdates": [],
	"_idRow": 109250,
	"_sName": "aim_uspdust",
	"_sText": "Little aim & usp map"
}