{
	"_aAlternateFileSources": null,
	"_aFiles": [
		{
			"_aMetadata": {
				"_aArchiveFileTree": [
					"Fy_iceworld_DW_V2.bsp"
				],
				"_sMimeType": "application/x-rar"
			},
			"_bContainsExe": false,
			"_idRow": 354317,
			"_nDownloadCount": 1436,
			"_nFilesize": 231872,
			"_sAnalysisResult": "File passed analysis",
			"_sAnalysisState": "done",
			"_sDescription": "",
			"_sDownloadUrl": "https://gamebanana.com/dl/354317",
			"_sFile": "fy_iceworld_dw_v2.rar",
			"_sMd5Checksum": "",
			"_tsDateAdded": 1166816319
		}
	],
	"_aLatestUpdates": [],
	"_idRow": 112876,
	"_sName": "fy_iceworld_dw_v2",
	"_sText": "This is my second version of the map Fy_iceworld_DW. This one is more stable than teh other one. (much more stable) I have added a 3d skybox to it (the first one i have ever made so dont complain!) and most of the displacement is fixed now. PLEASE coment!"
}