{
	"_aAlternateFileSources": null,
	"_aFiles": [
		{
			"_aMetadata": {
				"_aArchiveFileTree": [
					"ii_theuprise.bsp"
				],
				"_sMimeType": "application/zip"
			},
			"_bContainsExe": false,
			"_idRow": 361741,
			"_nDownloadCount": 1266,
			"_nFilesize": 506875,
			"_sAnalysisResult": "File passed analysis",
			"_sAnalysisState": "done",
			"_sDescription": "",
			"_sDownloadUrl": "https://gamebanana.com/dl/361741",
			"_sFile": "ii_theuprise.zip",
			"_sMd5Checksum": "",
			"_tsDateAdded": 1112307758
		}
	],
	"_aLatestUpdates": [],
	"_idRow": 115109,
	"_sName": "ii_theuprise",
	"_sText": "Immortal Infantry Clan Map,\r\nwww.immortal-infantry.com/maps\r\nii_theuprise\r\nMap made by -=][-][=-Silent"
}