{
	"_aAlternateFileSources": null,
	"_aFiles": [
		{
			"_aMetadata": {
				"_aArchiveFileTree": [
					"The_Shire_LOTR.bsp"
				],
				"_sMimeType": "application/zip"
			},
			"_bContainsExe": false,
			"_idRow": 360803,
			"_nDownloadCount": 2832,
			"_nFilesize": 4432179,
			"_sAnalysisResult": "File passed analysis",
			"_sAnalysisState": "done",
			"_sDescription": "",
			"_sDownloadUrl": "https://gamebanana.com/dl/360803",
			"_sFile": "the_shire_lotr.zip",
			"_sMd5Checksum": "",
			"_tsDateAdded": 1123740639
		}
	],
	"_aLatestUpdates": [],
	"_idRow": 116695,
	"_sName": "the_shire_lotr",
	"_sText": "This is the completed version, enjoy!"
}