{
	"_aAlternateFileSources": null,
	"_aFiles": [
		{
			"_aMetadata": {
				"_aArchiveFileTree": [
					"awp_map_2k7.bsp",
					"awp_map_2k7.txt"
				],
				"_sMimeType": "application/zip"
			},
			"_bContainsExe": false,
			"_idRow": 351340,
			"_nDownloadCount": 1631,
			"_nFilesize": 47380,
			"_sAnalysisResult": "File passed analysis",
			"_sAnalysisState": "done",
			"_sDescription": "",
			"_sDownloadUrl": "https://gamebanana.com/dl/351340",
			"_sFile": "awp_map_2k7.zip",
			"_sMd5Checksum": "",
			"_tsDateAdded": 1180190121
		}
	],
	"_aLatestUpdates": [],
	"_idRow": 118863,
	"_sName": "awp_map_2k7",
	"_sText": "===============================\r\nawp_map_2k7:\r\n\r\nClassic CS remake of awp_map by \"OSi\"\r\n\r\nThanks to the Author of awp_map.\r\n\r\n-------------------------------\r\nRules:\r\n\r\nTerrorists: Kill CT's with AWP.\r\n\r\nCounter-Terrorists:  Kill T's with AWP. \r\n\r\nSupports 42 players.\r\n\r\nSuggestions? ICQ: 175345068\r\n=============================="
}