{
	"_aAlternateFileSources": null,
	"_aFiles": [
		{
			"_aMetadata": {
				"_aArchiveFileTree": [
					"Twobasewar7.bsp",
					"Twobasewar7.prt",
					"Twobasewar7.vmf",
					"twobasewar7.log",
					"twobasewar7.nav"
				],
				"_sMimeType": "application/zip"
			},
			"_bContainsExe": false,
			"_idRow": 314309,
			"_nDownloadCount": 1571,
			"_nFilesize": 200603,
			"_sAnalysisResult": "File passed analysis",
			"_sAnalysisState": "done",
			"_sDescription": "",
			"_sDownloadUrl": "https://gamebanana.com/dl/314309",
			"_sFile": "_2425-.zip",
			"_sMd5Checksum": "",
			"_tsDateAdded": 1299340003
		}
	],
	"_aLatestUpdates": [],
	"_idRow": 120151,
	"_sName": "Two_base_war",
	"_sText": "This is a small battle arena, enjoy!"
}