{
	"_aAlternateFileSources": null,
	"_aFiles": [
		{
			"_aMetadata": {
				"_aArchiveFileTree": {
					"fun_skydive": {
						"cstrike": {
							"0": "I_N_S_T_A_L_L_A_T_I_O_N.txt",
							"maps": {
								"0": "fun_skydive.bsp",
								"1": "fun_skydive.nav",
								"graphs": [
									"fun_skydive.ain"
								],
								"soundcache": [
									"fun_skydive.cache"
								]
							}
						}
					}
				},
				"_sMimeType": "application/x-rar"
			},
			"_bContainsExe": false,
			"_idRow": 361392,
			"_nDownloadCount": 2914,
			"_nFilesize": 4376443,
			"_sAnalysisResult": "File passed analysis",
			"_sAnalysisState": "done",
			"_sDescription": "",
			"_sDownloadUrl": "https://gamebanana.com/dl/361392",
			"_sFile": "fun_skydive.rar",
			"_sMd5Checksum": "",
			"_tsDateAdded": 1116709065
		}
	],
	"_aLatestUpdates": [],
	"_idRow": 120664,
	"_sName": "fun_skydive",
	"_sText": "Fall and die."
}