{
	"_aAlternateFileSources": null,
	"_aFiles": [
		{
			"_aMetadata": {
				"_aArchiveFileTree": {
					"maps": [
						"picoschool.bsp",
						"picoschool.nav",
						"picoschool.txt"
					]
				},
				"_sMimeType": "application/zip"
			},
			"_bContainsExe": false,
			"_idRow": 351889,
			"_nDownloadCount": 2464,
			"_nFilesize": 4823552,
			"_sAnalysisResult": "File passed analysis",
			"_sAnalysisState": "done",
			"_sDescription": "",
			"_sDownloadUrl": "https://gamebanana.com/dl/351889",
			"_sFile": "picoschool.zip",
			"_sMd5Checksum": "",
			"_tsDateAdded": 1177607851
		}
	],
	"_aLatestUpdates": [],
	"_idRow": 120922,
	"_sName": "picoschool",
	"_sText": "Picoschool by Nuke of lawgiver.us and silentrecon of newgrounds.com\r\nFlash Game of picoschool by TomFulp of newgrounds.com\r\nMusic use by map is by kamakazi-AKA-crazy of newgrounds.com\r\n\r\nBackground:\r\n\r\nThis is for Picoday 2007.I just wanted to do a map base of a flash game for sometime now.\r\nI try to make the map as close as I can to the real thing as I can do.\r\n\r\nCt and T\r\n\r\nThis is a deathmatch map so go kill each other\r\n\r\nNotes:\r\n\r\nI do not pico school tom does so don't send me any money give it all to him\r\nI did not make this map to make money I made this map as a fan of that flash game\r\nI also don't own the music so give kamakazi all the money as well\r\n\r\nVisit\r\n\r\nNewgrounds.com\r\nLawgiver.us\r\nfpsbanana.com\r\n\r\n63.211.110.144:27015 is the server this map will be on so please enjoy it\r\n\r\nThe bsp is bspzip\r\nThe nav file is custom\r\n\r\n( and I know what your going to say but I been working on this map since early march and I got it done on the 10th and I was going to put it out on the 17th but then the shooting so I hold back untill today and plus I wanted to move on to other projects as well )"
}