{
	"_aAlternateFileSources": null,
	"_aFiles": [
		{
			"_aMetadata": {
				"_aArchiveFileTree": [
					"surf_log.bsp"
				],
				"_sMimeType": "application/zip"
			},
			"_bContainsExe": false,
			"_idRow": 331975,
			"_nDownloadCount": 1344,
			"_nFilesize": 3124063,
			"_sAnalysisResult": "File passed analysis",
			"_sAnalysisState": "done",
			"_sDescription": "",
			"_sDownloadUrl": "https://gamebanana.com/dl/331975",
			"_sFile": "surf_log_2.zip",
			"_sMd5Checksum": "",
			"_tsDateAdded": 1242023315
		}
	],
	"_aLatestUpdates": [],
	"_idRow": 122452,
	"_sName": "surf_log",
	"_sText": "This is the first surf map I made (first one ive released)\r\nIts a little surf map with jail and bomb site... When I made this map i didnt know how to make good surf ramps, so they are not the best\r\n\r\n\r\nThis map will need Noblock so people wont get stuck at the teleports\r\n\r\nAlso a special thanks to komaokc for the skybox\r\n\r\nFIXED THE TEXTURE x'D"
}