{
	"_aAlternateFileSources": null,
	"_aFiles": [
		{
			"_aMetadata": {
				"_aArchiveFileTree": {
					"maps": [
						"glass_psychotic.bsp",
						"glass_psychotic.nav"
					],
					"materials": {
						"psychoticdeath": {
							"peachescastle": [
								"brickwork.vmt",
								"brickwork.vtf",
								"psycho.vmt",
								"psycho.vtf"
							]
						}
					}
				},
				"_sMimeType": "application/zip"
			},
			"_bContainsExe": false,
			"_idRow": 358093,
			"_nDownloadCount": 1541,
			"_nFilesize": 504001,
			"_sAnalysisResult": "File passed analysis",
			"_sAnalysisState": "done",
			"_sDescription": "",
			"_sDownloadUrl": "https://gamebanana.com/dl/358093",
			"_sFile": "638_cstrike_9.zip",
			"_sMd5Checksum": "",
			"_tsDateAdded": 1146676324
		}
	],
	"_aLatestUpdates": [],
	"_idRow": 123543,
	"_sName": "glass_psychotic",
	"_sText": "Just a fun glass map I thought I would make. not much of a looker, but try playing on it :D"
}