{
	"_aAlternateFileSources": null,
	"_aFiles": [
		{
			"_aMetadata": {
				"_aArchiveFileTree": [
					"bhop_decimus.bsp"
				],
				"_sMimeType": "application/x-rar"
			},
			"_bContainsExe": false,
			"_idRow": 463433,
			"_nDownloadCount": 123,
			"_nFilesize": 16154000,
			"_sAnalysisResult": "File passed analysis",
			"_sAnalysisResultCode": "ok",
			"_sAnalysisState": "done",
			"_sAvastAvResult": "clean",
			"_sClamAvResult": "clean",
			"_sDescription": "",
			"_sDownloadUrl": "https://gamebanana.com/dl/463433",
			"_sFile": "bhop_decimus_f01b9.rar",
			"_sMd5Checksum": "",
			"_tsDateAdded": 1589734567
		}
	],
	"_aLatestUpdates": [],
	"_idRow": 124807,
	"_sName": "bhop_decimus (CSS)",
	"_sText": "Original map by SmokedOut<br>Port from CS:GO"
}