{
	"_aAlternateFileSources": null,
	"_aFiles": [
		{
			"_aMetadata": {
				"_aArchiveFileTree": [
					"bhop_pipin_v2.bsp"
				],
				"_sMimeType": "application/x-rar"
			},
			"_bContainsExe": false,
			"_idRow": 282080,
			"_nDownloadCount": 381,
			"_nFilesize": 11279217,
			"_sAnalysisResult": "File passed analysis",
			"_sAnalysisState": "done",
			"_sDescription": "",
			"_sDownloadUrl": "https://gamebanana.com/dl/282080",
			"_sFile": "bhop_pipin_v2_2.rar",
			"_sMd5Checksum": "",
			"_tsDateAdded": 1438183940
		}
	],
	"_aLatestUpdates": [
		{
			"_aChangeLog": [
				{
					"cat": "-",
					"text": "missing textures"
				}
			],
			"_sText": "fixed the missing textures",
			"_sTitle": "missing texture fix",
			"_tsDateAdded": 1439581134
		}
	],
	"_idRow": 125743,
	"_sName": "bhop_pipin",
	"_sText": "medium size map with a bunch of hard jumps!\r\n\r\nedit: new version \r\n•fixed missing textures"
}