{
	"_aAlternateFileSources": null,
	"_aFiles": [
		{
			"_aMetadata": {
				"_aArchiveFileTree": [
					"bhop_scarlet_css.bsp"
				],
				"_sMimeType": "application/x-rar"
			},
			"_bContainsExe": false,
			"_idRow": 494750,
			"_nDownloadCount": 116,
			"_nFilesize": 7585184,
			"_sAnalysisResult": "File passed analysis",
			"_sAnalysisState": "done",
			"_sClamAvResult": "clean",
			"_sDescription": "",
			"_sDownloadUrl": "https://gamebanana.com/dl/494750",
			"_sFile": "bhop_scarlet_css.rar",
			"_sMd5Checksum": "",
			"_tsDateAdded": 1604767260
		}
	],
	"_aLatestUpdates": [],
	"_idRow": 125917,
	"_sName": "bhop_scarlet_css",
	"_sText": "Tier 2 linear strafe map<br><br>Thank you Ward for testing and Fool for porting and support."
}