{
	"_aAlternateFileSources": null,
	"_aFiles": [
		{
			"_aMetadata": {
				"_aArchiveFileTree": [
					"bhop_xtreme_final.bsp"
				],
				"_sMimeType": "application/x-rar"
			},
			"_bContainsExe": false,
			"_idRow": 327056,
			"_nDownloadCount": 1789,
			"_nFilesize": 2115578,
			"_sAnalysisResult": "File passed analysis",
			"_sAnalysisState": "done",
			"_sDescription": "",
			"_sDownloadUrl": "https://gamebanana.com/dl/327056",
			"_sFile": "bhop_xtreme_final.rar",
			"_sMd5Checksum": "",
			"_tsDateAdded": 1258846274
		}
	],
	"_aLatestUpdates": [],
	"_idRow": 126380,
	"_sName": "bhop_xtreme_final",
	"_sText": "This is the full version on the bhop_xtreme beta version.\r\nIts much harder and i have add many step on the full verssion.\r\n\r\nIts around 20 to 25 players.\r\nYou get scout and deagle when you join the map. And awp when you beat the map"
}