{
	"_aAlternateFileSources": null,
	"_aFiles": [
		{
			"_aMetadata": {
				"_aArchiveFileTree": [
					"ba_jail_electric_aero_v1_1.bsp",
					"readme.txt"
				],
				"_sMimeType": "application/zip"
			},
			"_bContainsExe": false,
			"_idRow": 290548,
			"_nDownloadCount": 2970,
			"_nFilesize": 41890627,
			"_sAnalysisResult": "File passed analysis",
			"_sAnalysisResultCode": "ok",
			"_sAnalysisState": "done",
			"_sAvastAvResult": "clean",
			"_sClamAvResult": "clean",
			"_sDescription": "",
			"_sDownloadUrl": "https://gamebanana.com/dl/290548",
			"_sFile": "ba_jail_electric_aero_v1_1.zip",
			"_sMd5Checksum": "",
			"_tsDateAdded": 1388417472
		}
	],
	"_aLatestUpdates": [],
	"_idRow": 129177,
	"_sName": "ba_jail_electric_aero_v1.1",
	"_sText": "Hi,\r\nthis is a map in electric_vip_v2 layout.\r\nIn Despite of that, i've made it from the very beginning.\r\nSomething is different and other things are very similiar. \r\nBut the new minigames are amazing!\r\n\r\n64 Slots (42 T : 22 CT)\r\n12 Minigames (DriveDown, ShootDown, WrongChairs, Skipping, etc.)\r\n\r\nless words are sometimes more ^^"
}