{
	"_aAlternateFileSources": null,
	"_aFiles": [
		{
			"_aMetadata": {
				"_aArchiveFileTree": [
					"README.rtf",
					"ba_jail_lockdown_halloween.bsp"
				],
				"_sMimeType": "application/zip"
			},
			"_bContainsExe": false,
			"_idRow": 291922,
			"_nDownloadCount": 1129,
			"_nFilesize": 50317077,
			"_sAnalysisResult": "File passed analysis",
			"_sAnalysisResultCode": "ok",
			"_sAnalysisState": "done",
			"_sAvastAvResult": "clean",
			"_sClamAvResult": "clean",
			"_sDescription": "",
			"_sDownloadUrl": "https://gamebanana.com/dl/291922",
			"_sFile": "ba_jail_lockdown_halloween.zip",
			"_sMd5Checksum": "",
			"_tsDateAdded": 1381409293
		}
	],
	"_aLatestUpdates": [],
	"_idRow": 129342,
	"_sName": "ba_jail_lockdown_halloween",
	"_sText": "Hey guys !\r\nToday i show you the beginning of my work for Halloween !\r\nIgnamarte and me are working on editing 4 maps.\r\n\r\nAll the information about this map are here :\r\n\r\nhttp://css.gamebanana.com/maps/124944\r\n\r\nWhat is new ?\r\n- Lighting\r\n- Custom texture\r\n- Custom models\r\n- New Hats\r\n- Custom music\r\n\r\nThanks to Tophattwaffle who let me do it.\r\n\r\nHappy  Halloween !"
}