{
	"_aAlternateFileSources": null,
	"_aFiles": [
		{
			"_aMetadata": {
				"_aArchiveFileTree": [
					"zm_noohs.bsp",
					"zm_noohs0000.jpg",
					"zm_noohs0001.jpg",
					"zm_noohs0002.jpg",
					"zm_noohs0003.jpg",
					"zm_noohs0004.jpg",
					"zm_noohs0005.jpg",
					"zm_noohs0006.jpg"
				],
				"_sMimeType": "application/zip"
			},
			"_bContainsExe": false,
			"_idRow": 330411,
			"_nDownloadCount": 1265,
			"_nFilesize": 5431052,
			"_sAnalysisResult": "File passed analysis",
			"_sAnalysisState": "done",
			"_sDescription": "",
			"_sDownloadUrl": "https://gamebanana.com/dl/330411",
			"_sFile": "zm_noohs_2.zip",
			"_sMd5Checksum": "",
			"_tsDateAdded": 1247762147
		}
	],
	"_aLatestUpdates": [],
	"_idRow": 132471,
	"_sName": "zm_noohs",
	"_sText": "This map has no secrets. It is a classic zombiemod map. There is an invisible maze under the bleachers."
}