{
	"_aAlternateFileSources": null,
	"_aFiles": [
		{
			"_aMetadata": {
				"_aArchiveFileTree": [
					"aim_boxy_walkways_gg.bsp"
				],
				"_sMimeType": "application/zip"
			},
			"_bContainsExe": false,
			"_idRow": 346274,
			"_nDownloadCount": 1565,
			"_nFilesize": 277317,
			"_sAnalysisResult": "File passed analysis",
			"_sAnalysisState": "done",
			"_sDescription": "",
			"_sDownloadUrl": "https://gamebanana.com/dl/346274",
			"_sFile": "aim_boxy_walkways_gg.zip",
			"_sMd5Checksum": "",
			"_tsDateAdded": 1196896137
		}
	],
	"_aLatestUpdates": [],
	"_idRow": 133219,
	"_sName": "aim_boxy_walkways_gg",
	"_sText": "Please don't try to take credit for this map... unless your me, then its OK :P."
}