{
	"_aAlternateFileSources": null,
	"_aFiles": [
		{
			"_aMetadata": {
				"_aArchiveFileTree": [
					"gg_ag_texture_svg_beta1.bsp",
					"readme.txt"
				],
				"_sMimeType": "application/zip"
			},
			"_bContainsExe": false,
			"_idRow": 337760,
			"_nDownloadCount": 1084,
			"_nFilesize": 125199,
			"_sAnalysisResult": "File passed analysis",
			"_sAnalysisState": "done",
			"_sDescription": "",
			"_sDownloadUrl": "https://gamebanana.com/dl/337760",
			"_sFile": "gg_ag_texture_svg_beta1.zip",
			"_sMd5Checksum": "",
			"_tsDateAdded": 1223691213
		}
	],
	"_aLatestUpdates": [],
	"_idRow": 133552,
	"_sName": "gg_ag_texture_svg_beta1",
	"_sText": "This is the first beta version of this map, next version will contain better lighting"
}