{
	"_aAlternateFileSources": null,
	"_aFiles": [
		{
			"_aMetadata": {
				"_aArchiveFileTree": [
					"gg_hsx_pillar.bsp"
				],
				"_sMimeType": "application/x-rar"
			},
			"_bContainsExe": false,
			"_idRow": 322365,
			"_nDownloadCount": 1048,
			"_nFilesize": 546329,
			"_sAnalysisResult": "File passed analysis",
			"_sAnalysisState": "done",
			"_sDescription": "",
			"_sDownloadUrl": "https://gamebanana.com/dl/322365",
			"_sFile": "gg_hsx_pillar.rar",
			"_sMd5Checksum": "",
			"_tsDateAdded": 1275378111
		}
	],
	"_aLatestUpdates": [],
	"_idRow": 135304,
	"_sName": "gg_hsx_pillar",
	"_sText": "This is another of my own original maps. Originally created for a tournament that my clan was having, it never got submitted and so ends up here. It is well liked on our server though."
}