{
	"_aAlternateFileSources": null,
	"_aFiles": [
		{
			"_aMetadata": {
				"_aArchiveFileTree": {
					"gg_sik": [
						"gg_sik.bsp"
					]
				},
				"_sMimeType": "application/zip"
			},
			"_bContainsExe": false,
			"_idRow": 336407,
			"_nDownloadCount": 1112,
			"_nFilesize": 1190101,
			"_sAnalysisResult": "File passed analysis",
			"_sAnalysisState": "done",
			"_sDescription": "",
			"_sDownloadUrl": "https://gamebanana.com/dl/336407",
			"_sFile": "gg_sik.zip",
			"_sMd5Checksum": "",
			"_tsDateAdded": 1228261539
		}
	],
	"_aLatestUpdates": [],
	"_idRow": 136534,
	"_sName": "gg_sik",
	"_sText": "A GunGame map I made, it has four levels and each one has different things to hide behind.\r\n\r\nTHAY-imagine-\r\n\r\n<object width=\"280\"><param name=\"movie\" value=\"http://www.youtube.com/v/p_mK_xU83As&hl=en&fs=1&color1=0x3a3a3a&color2=0x999999\"></param><param name=\"allowFullScreen\" value=\"true\"></param><param name=\"allowscriptaccess\" value=\"always\"></param><embed src=\"http://www.youtube.com/v/p_mK_xU83As&hl=en&fs=1&color1=0x3a3a3a&color2=0x999999\" type=\"application/x-shockwave-flash\" allowscriptaccess=\"always\" allowfullscreen=\"true\" width=\"280\"></embed></object>"
}