{
	"_aAlternateFileSources": null,
	"_aFiles": [
		{
			"_aMetadata": {
				"_aArchiveFileTree": [
					"gg_snowshoes.bsp"
				],
				"_sMimeType": "application/x-rar"
			},
			"_bContainsExe": false,
			"_idRow": 336222,
			"_nDownloadCount": 1101,
			"_nFilesize": 136769,
			"_sAnalysisResult": "File passed analysis",
			"_sAnalysisState": "done",
			"_sDescription": "",
			"_sDownloadUrl": "https://gamebanana.com/dl/336222",
			"_sFile": "gg_snowshoes_2.rar",
			"_sMd5Checksum": "",
			"_tsDateAdded": 1229034636
		}
	],
	"_aLatestUpdates": [],
	"_idRow": 136694,
	"_sName": "gg_snowshoes",
	"_sText": "This is a bad map but yh.."
}