{
	"_aAlternateFileSources": null,
	"_aFiles": [
		{
			"_aMetadata": {
				"_aArchiveFileTree": [
					"hangar.vmf"
				]
			},
			"_bContainsExe": false,
			"_idRow": 46328,
			"_nDownloadCount": 922,
			"_nFilesize": 12529,
			"_sAnalysisResult": "File passed analysis",
			"_sAnalysisState": "done",
			"_sClamAvResult": "clean",
			"_sDescription": "",
			"_sDownloadUrl": "https://gamebanana.com/dl/46328",
			"_sFile": "hangar_2.rar",
			"_sMd5Checksum": "",
			"_tsDateAdded": 1281818655
		}
	],
	"_aLatestUpdates": [],
	"_idRow": 2462,
	"_sName": "hangar/warehouse",
	"_sText": "123"
}