{
	"_aAlternateFileSources": null,
	"_aFiles": [
		{
			"_aMetadata": {
				"_aArchiveFileTree": [
					"Exploding-Toilet.bsp",
					"Exploding-Toilet.vmf",
					"exploding-toilet.nav"
				]
			},
			"_bContainsExe": false,
			"_idRow": 46924,
			"_nDownloadCount": 472,
			"_nFilesize": 17562,
			"_sAnalysisResult": "File passed analysis",
			"_sAnalysisResultCode": "ok",
			"_sAnalysisState": "done",
			"_sAvastAvResult": "clean",
			"_sClamAvResult": "clean",
			"_sDescription": "",
			"_sDownloadUrl": "https://gamebanana.com/dl/46924",
			"_sFile": "exploding-toilet_2.rar",
			"_sMd5Checksum": "",
			"_tsDateAdded": 1235712561
		}
	],
	"_aLatestUpdates": [],
	"_idRow": 3132,
	"_sName": "Exploding Toilet",
	"_sText": "This is a basic toilet that explodes when you press the button beside it.\r\n\r\nIf used in a map or any other project give me credit.\r\n\r\nYou may not edit this toilet without my consent.\r\n\r\n-Lt. Rico"
}