{
	"_aAlternateFileSources": null,
	"_aFiles": [
		{
			"_aMetadata": {
				"_aArchiveFileTree": {
					"zm_Moon": [
						"zm_Moon_v1.bsp"
					]
				}
			},
			"_bContainsExe": false,
			"_idRow": 1280367,
			"_nDownloadCount": 7,
			"_nFilesize": 27199318,
			"_sAnalysisResult": "File passed analysis",
			"_sAnalysisResultCode": "ok",
			"_sAnalysisState": "done",
			"_sAvastAvResult": "clean",
			"_sClamAvResult": "clean",
			"_sDescription": "zm_Moon",
			"_sDownloadUrl": "https://gamebanana.com/dl/1280367",
			"_sFile": "zm_moon.7z",
			"_sMd5Checksum": "8f75f79f284da896f401dcd2b420705b",
			"_tsDateAdded": 1726381322
		}
	],
	"_aLatestUpdates": [],
	"_idRow": 542318,
	"_sName": "zm_Moon",
	"_sText": "Space colony on the Moon."
}