{
	"_aAlternateFileSources": null,
	"_aFiles": [
		{
			"_aMetadata": {
				"_aArchiveFileTree": {
					"cstrike": {
						"maps": [
							"cs_abbey.bsp",
							"cs_abbey.nav",
							"cs_abbey.txt"
						],
						"materials": {
							"overviews": [
								"cs_abbey.vmt",
								"cs_abbey.vtf"
							]
						},
						"resource": {
							"overviews": [
								"cs_abbey.txt"
							]
						}
					}
				}
			},
			"_bContainsExe": false,
			"_idRow": 314025,
			"_nDownloadCount": 5882,
			"_nFilesize": 5869256,
			"_sAnalysisResult": "File passed analysis",
			"_sAnalysisState": "done",
			"_sDescription": "",
			"_sDownloadUrl": "https://gamebanana.com/dl/314025",
			"_sFile": "_2876-.zip",
			"_sMd5Checksum": "",
			"_tsDateAdded": 1300358778
		}
	],
	"_aLatestUpdates": [],
	"_idRow": 99477,
	"_sName": "cs_abbey",
	"_sText": "Brookshire Abbey - Hostage Rescue\r\n\r\nThe Brookshire Abbey in Enoch has been \r\ntaken by terrorists who demand the release\r\nof General Yukiya Amano for the release\r\nof two spiritual leaders. \r\n \r\nCounter-Terrorists: Enter the Terrorist\r\nstronghold and rescue the hostages. \r\nTake out the Terrorists without \r\njeopardizing the hostages.\r\n\r\nTerrorists: Prevent the Counter-Terrorist\r\nforce from rescuing the hostages. \r\n \r\nOther Notes: There are 2 hostages in \r\nthis mission and one hostage rescue zone\r\ndenoted by a red smoke grenade. \r\n\r\nBy: Redbodega\r\nwww.redbodega.com"
}